dabft/__init__.py
dabft/main.py
dabft-1.0.1.dist-info/METADATA
dabft-1.0.1.dist-info/WHEEL
dabft-1.0.1.dist-info/entry_points.txt
dabft-1.0.1.dist-info/licenses/LICENSE
dabft-1.0.1.dist-info/RECORD
